[
  {
    "match_id": 73,
    "match_number": 73,
    "stage": "16es de finale",
    "home_placeholder": "2A",
    "away_placeholder": "2B",
    "home_team": "",
    "home_code": "",
    "home_flag": "",
    "away_team": "",
    "away_code": "",
    "away_flag": "",
    "home_score_real": "",
    "away_score_real": "",
    "result_real": "",
    "shootout_winner": "",
    "pred_home_win": "",
    "pred_draw": "",
    "pred_away_win": "",
    "date": "Dimanche 28 juin (21 heures)",
    "city": "Los Angeles",
    "next_match_id": 89,
    "is_home_in_next": true,
    "loser_next_match_id": null,
    "is_loser_home_in_next": null
  },
  {
    "match_id": 74,
    "match_number": 74,
    "stage": "16es de finale",
    "home_placeholder": "1C",
    "away_placeholder": "2F",
    "home_team": "",
    "home_code": "",
    "home_flag": "",
    "away_team": "",
    "away_code": "",
    "away_flag": "",
    "home_score_real": "",
    "away_score_real": "",
    "result_real": "",
    "shootout_winner": "",
    "pred_home_win": "",
    "pred_draw": "",
    "pred_away_win": "",
    "date": "Lundi 29 juin (19 heures)",
    "city": "Houston",
    "next_match_id": 90,
    "is_home_in_next": true,
    "loser_next_match_id": null,
    "is_loser_home_in_next": null
  },
  {
    "match_id": 75,
    "match_number": 75,
    "stage": "16es de finale",
    "home_placeholder": "1E",
    "away_placeholder": "3ABCDF",
    "home_team": "",
    "home_code": "",
    "home_flag": "",
    "away_team": "",
    "away_code": "",
    "away_flag": "",
    "home_score_real": "",
    "away_score_real": "",
    "result_real": "",
    "shootout_winner": "",
    "pred_home_win": "",
    "pred_draw": "",
    "pred_away_win": "",
    "date": "Lundi 29 juin (22h30)",
    "city": "Boston",
    "next_match_id": 89,
    "is_home_in_next": false,
    "loser_next_match_id": null,
    "is_loser_home_in_next": null
  },
  {
    "match_id": 76,
    "match_number": 76,
    "stage": "16es de finale",
    "home_placeholder": "1F",
    "away_placeholder": "2C",
    "home_team": "",
    "home_code": "",
    "home_flag": "",
    "away_team": "",
    "away_code": "",
    "away_flag": "",
    "home_score_real": "",
    "away_score_real": "",
    "result_real": "",
    "shootout_winner": "",
    "pred_home_win": "",
    "pred_draw": "",
    "pred_away_win": "",
    "date": "Mardi 30 juin (3 heures)",
    "city": "Monterrey",
    "next_match_id": 91,
    "is_home_in_next": true,
    "loser_next_match_id": null,
    "is_loser_home_in_next": null
  },
  {
    "match_id": 77,
    "match_number": 77,
    "stage": "16es de finale",
    "home_placeholder": "2E",
    "away_placeholder": "2I",
    "home_team": "",
    "home_code": "",
    "home_flag": "",
    "away_team": "",
    "away_code": "",
    "away_flag": "",
    "home_score_real": "",
    "away_score_real": "",
    "result_real": "",
    "shootout_winner": "",
    "pred_home_win": "",
    "pred_draw": "",
    "pred_away_win": "",
    "date": "Mardi 30 juin (19 heures)",
    "city": "Dallas",
    "next_match_id": 90,
    "is_home_in_next": false,
    "loser_next_match_id": null,
    "is_loser_home_in_next": null
  },
  {
    "match_id": 78,
    "match_number": 78,
    "stage": "16es de finale",
    "home_placeholder": "1I",
    "away_placeholder": "3CDFGH",
    "home_team": "",
    "home_code": "",
    "home_flag": "",
    "away_team": "",
    "away_code": "",
    "away_flag": "",
    "home_score_real": "",
    "away_score_real": "",
    "result_real": "",
    "shootout_winner": "",
    "pred_home_win": "",
    "pred_draw": "",
    "pred_away_win": "",
    "date": "Mardi 30 juin (23 heures)",
    "city": "New York/New Jersey",
    "next_match_id": 91,
    "is_home_in_next": false,
    "loser_next_match_id": null,
    "is_loser_home_in_next": null
  },
  {
    "match_id": 79,
    "match_number": 79,
    "stage": "16es de finale",
    "home_placeholder": "1A",
    "away_placeholder": "3CEFHI",
    "home_team": "",
    "home_code": "",
    "home_flag": "",
    "away_team": "",
    "away_code": "",
    "away_flag": "",
    "home_score_real": "",
    "away_score_real": "",
    "result_real": "",
    "shootout_winner": "",
    "pred_home_win": "",
    "pred_draw": "",
    "pred_away_win": "",
    "date": "Mercredi 1er juillet (3 heures)",
    "city": "Mexico City",
    "next_match_id": 92,
    "is_home_in_next": true,
    "loser_next_match_id": null,
    "is_loser_home_in_next": null
  },
  {
    "match_id": 80,
    "match_number": 80,
    "stage": "16es de finale",
    "home_placeholder": "1L",
    "away_placeholder": "3EHIJK",
    "home_team": "",
    "home_code": "",
    "home_flag": "",
    "away_team": "",
    "away_code": "",
    "away_flag": "",
    "home_score_real": "",
    "away_score_real": "",
    "result_real": "",
    "shootout_winner": "",
    "pred_home_win": "",
    "pred_draw": "",
    "pred_away_win": "",
    "date": "Mercredi 1er juillet (18 heures)",
    "city": "Atlanta",
    "next_match_id": 92,
    "is_home_in_next": false,
    "loser_next_match_id": null,
    "is_loser_home_in_next": null
  },
  {
    "match_id": 81,
    "match_number": 81,
    "stage": "16es de finale",
    "home_placeholder": "1G",
    "away_placeholder": "3AEHIJ",
    "home_team": "",
    "home_code": "",
    "home_flag": "",
    "away_team": "",
    "away_code": "",
    "away_flag": "",
    "home_score_real": "",
    "away_score_real": "",
    "result_real": "",
    "shootout_winner": "",
    "pred_home_win": "",
    "pred_draw": "",
    "pred_away_win": "",
    "date": "Mercredi 1er juillet (22 heures)",
    "city": "Seattle",
    "next_match_id": 94,
    "is_home_in_next": true,
    "loser_next_match_id": null,
    "is_loser_home_in_next": null
  },
  {
    "match_id": 82,
    "match_number": 82,
    "stage": "16es de finale",
    "home_placeholder": "1D",
    "away_placeholder": "3BEFIJ",
    "home_team": "",
    "home_code": "",
    "home_flag": "",
    "away_team": "",
    "away_code": "",
    "away_flag": "",
    "home_score_real": "",
    "away_score_real": "",
    "result_real": "",
    "shootout_winner": "",
    "pred_home_win": "",
    "pred_draw": "",
    "pred_away_win": "",
    "date": "Jeudi 2 juillet (2 heures)",
    "city": "San Francisco Bay Area",
    "next_match_id": 94,
    "is_home_in_next": false,
    "loser_next_match_id": null,
    "is_loser_home_in_next": null
  },
  {
    "match_id": 83,
    "match_number": 83,
    "stage": "16es de finale",
    "home_placeholder": "1H",
    "away_placeholder": "2J",
    "home_team": "",
    "home_code": "",
    "home_flag": "",
    "away_team": "",
    "away_code": "",
    "away_flag": "",
    "home_score_real": "",
    "away_score_real": "",
    "result_real": "",
    "shootout_winner": "",
    "pred_home_win": "",
    "pred_draw": "",
    "pred_away_win": "",
    "date": "Jeudi 2 juillet (21 heures)",
    "city": "Los Angeles",
    "next_match_id": 93,
    "is_home_in_next": true,
    "loser_next_match_id": null,
    "is_loser_home_in_next": null
  },
  {
    "match_id": 84,
    "match_number": 84,
    "stage": "16es de finale",
    "home_placeholder": "2K",
    "away_placeholder": "2L",
    "home_team": "",
    "home_code": "",
    "home_flag": "",
    "away_team": "",
    "away_code": "",
    "away_flag": "",
    "home_score_real": "",
    "away_score_real": "",
    "result_real": "",
    "shootout_winner": "",
    "pred_home_win": "",
    "pred_draw": "",
    "pred_away_win": "",
    "date": "Vendredi 3 juillet (1 heure)",
    "city": "Toronto",
    "next_match_id": 93,
    "is_home_in_next": false,
    "loser_next_match_id": null,
    "is_loser_home_in_next": null
  },
  {
    "match_id": 85,
    "match_number": 85,
    "stage": "16es de finale",
    "home_placeholder": "1B",
    "away_placeholder": "3EFGIJ",
    "home_team": "",
    "home_code": "",
    "home_flag": "",
    "away_team": "",
    "away_code": "",
    "away_flag": "",
    "home_score_real": "",
    "away_score_real": "",
    "result_real": "",
    "shootout_winner": "",
    "pred_home_win": "",
    "pred_draw": "",
    "pred_away_win": "",
    "date": "Vendredi 3 juillet (5 heures)",
    "city": "Vancouver",
    "next_match_id": 96,
    "is_home_in_next": true,
    "loser_next_match_id": null,
    "is_loser_home_in_next": null
  },
  {
    "match_id": 86,
    "match_number": 86,
    "stage": "16es de finale",
    "home_placeholder": "2D",
    "away_placeholder": "2G",
    "home_team": "",
    "home_code": "",
    "home_flag": "",
    "away_team": "",
    "away_code": "",
    "away_flag": "",
    "home_score_real": "",
    "away_score_real": "",
    "result_real": "",
    "shootout_winner": "",
    "pred_home_win": "",
    "pred_draw": "",
    "pred_away_win": "",
    "date": "Vendredi 3 juillet (20 heures)",
    "city": "Dallas",
    "next_match_id": 95,
    "is_home_in_next": true,
    "loser_next_match_id": null,
    "is_loser_home_in_next": null
  },
  {
    "match_id": 87,
    "match_number": 87,
    "stage": "16es de finale",
    "home_placeholder": "1J",
    "away_placeholder": "2H",
    "home_team": "",
    "home_code": "",
    "home_flag": "",
    "away_team": "",
    "away_code": "",
    "away_flag": "",
    "home_score_real": "",
    "away_score_real": "",
    "result_real": "",
    "shootout_winner": "",
    "pred_home_win": "",
    "pred_draw": "",
    "pred_away_win": "",
    "date": "Samedi 4 juillet (Minuit)",
    "city": "Miami",
    "next_match_id": 96,
    "is_home_in_next": false,
    "loser_next_match_id": null,
    "is_loser_home_in_next": null
  },
  {
    "match_id": 88,
    "match_number": 88,
    "stage": "16es de finale",
    "home_placeholder": "1K",
    "away_placeholder": "3DEIJL",
    "home_team": "",
    "home_code": "",
    "home_flag": "",
    "away_team": "",
    "away_code": "",
    "away_flag": "",
    "home_score_real": "",
    "away_score_real": "",
    "result_real": "",
    "shootout_winner": "",
    "pred_home_win": "",
    "pred_draw": "",
    "pred_away_win": "",
    "date": "Samedi 4 juillet (3h30)",
    "city": "Kansas City",
    "next_match_id": 95,
    "is_home_in_next": false,
    "loser_next_match_id": null,
    "is_loser_home_in_next": null
  },
  {
    "match_id": 89,
    "match_number": 89,
    "stage": "8es de finale",
    "home_placeholder": "W73",
    "away_placeholder": "W75",
    "home_team": "",
    "home_code": "",
    "home_flag": "",
    "away_team": "",
    "away_code": "",
    "away_flag": "",
    "home_score_real": "",
    "away_score_real": "",
    "result_real": "",
    "shootout_winner": "",
    "pred_home_win": "",
    "pred_draw": "",
    "pred_away_win": "",
    "date": "Samedi 4 juillet (19 heures)",
    "city": "Houston",
    "next_match_id": 97,
    "is_home_in_next": true,
    "loser_next_match_id": null,
    "is_loser_home_in_next": null
  },
  {
    "match_id": 90,
    "match_number": 90,
    "stage": "8es de finale",
    "home_placeholder": "W74",
    "away_placeholder": "W77",
    "home_team": "",
    "home_code": "",
    "home_flag": "",
    "away_team": "",
    "away_code": "",
    "away_flag": "",
    "home_score_real": "",
    "away_score_real": "",
    "result_real": "",
    "shootout_winner": "",
    "pred_home_win": "",
    "pred_draw": "",
    "pred_away_win": "",
    "date": "Samedi 4 juillet (23 heures)",
    "city": "Philadelphia",
    "next_match_id": 97,
    "is_home_in_next": false,
    "loser_next_match_id": null,
    "is_loser_home_in_next": null
  },
  {
    "match_id": 91,
    "match_number": 91,
    "stage": "8es de finale",
    "home_placeholder": "W76",
    "away_placeholder": "W78",
    "home_team": "",
    "home_code": "",
    "home_flag": "",
    "away_team": "",
    "away_code": "",
    "away_flag": "",
    "home_score_real": "",
    "away_score_real": "",
    "result_real": "",
    "shootout_winner": "",
    "pred_home_win": "",
    "pred_draw": "",
    "pred_away_win": "",
    "date": "Dimanche 5 juillet (22 heures)",
    "city": "New York/New Jersey",
    "next_match_id": 99,
    "is_home_in_next": true,
    "loser_next_match_id": null,
    "is_loser_home_in_next": null
  },
  {
    "match_id": 92,
    "match_number": 92,
    "stage": "8es de finale",
    "home_placeholder": "W79",
    "away_placeholder": "W80",
    "home_team": "",
    "home_code": "",
    "home_flag": "",
    "away_team": "",
    "away_code": "",
    "away_flag": "",
    "home_score_real": "",
    "away_score_real": "",
    "result_real": "",
    "shootout_winner": "",
    "pred_home_win": "",
    "pred_draw": "",
    "pred_away_win": "",
    "date": "Lundi 6 juillet (2 heures)",
    "city": "Mexico City",
    "next_match_id": 99,
    "is_home_in_next": false,
    "loser_next_match_id": null,
    "is_loser_home_in_next": null
  },
  {
    "match_id": 93,
    "match_number": 93,
    "stage": "8es de finale",
    "home_placeholder": "W83",
    "away_placeholder": "W84",
    "home_team": "",
    "home_code": "",
    "home_flag": "",
    "away_team": "",
    "away_code": "",
    "away_flag": "",
    "home_score_real": "",
    "away_score_real": "",
    "result_real": "",
    "shootout_winner": "",
    "pred_home_win": "",
    "pred_draw": "",
    "pred_away_win": "",
    "date": "Lundi 6 juillet (21 heures)",
    "city": "Dallas",
    "next_match_id": 98,
    "is_home_in_next": true,
    "loser_next_match_id": null,
    "is_loser_home_in_next": null
  },
  {
    "match_id": 94,
    "match_number": 94,
    "stage": "8es de finale",
    "home_placeholder": "W81",
    "away_placeholder": "W82",
    "home_team": "",
    "home_code": "",
    "home_flag": "",
    "away_team": "",
    "away_code": "",
    "away_flag": "",
    "home_score_real": "",
    "away_score_real": "",
    "result_real": "",
    "shootout_winner": "",
    "pred_home_win": "",
    "pred_draw": "",
    "pred_away_win": "",
    "date": "Mardi 7 juillet (2 heures)",
    "city": "Seattle",
    "next_match_id": 98,
    "is_home_in_next": false,
    "loser_next_match_id": null,
    "is_loser_home_in_next": null
  },
  {
    "match_id": 95,
    "match_number": 95,
    "stage": "8es de finale",
    "home_placeholder": "W86",
    "away_placeholder": "W88",
    "home_team": "",
    "home_code": "",
    "home_flag": "",
    "away_team": "",
    "away_code": "",
    "away_flag": "",
    "home_score_real": "",
    "away_score_real": "",
    "result_real": "",
    "shootout_winner": "",
    "pred_home_win": "",
    "pred_draw": "",
    "pred_away_win": "",
    "date": "Mardi 7 juillet (18 heures)",
    "city": "Atlanta",
    "next_match_id": 100,
    "is_home_in_next": true,
    "loser_next_match_id": null,
    "is_loser_home_in_next": null
  },
  {
    "match_id": 96,
    "match_number": 96,
    "stage": "8es de finale",
    "home_placeholder": "W85",
    "away_placeholder": "W87",
    "home_team": "",
    "home_code": "",
    "home_flag": "",
    "away_team": "",
    "away_code": "",
    "away_flag": "",
    "home_score_real": "",
    "away_score_real": "",
    "result_real": "",
    "shootout_winner": "",
    "pred_home_win": "",
    "pred_draw": "",
    "pred_away_win": "",
    "date": "Mardi 7 juillet (22 heures)",
    "city": "Vancouver",
    "next_match_id": 100,
    "is_home_in_next": false,
    "loser_next_match_id": null,
    "is_loser_home_in_next": null
  },
  {
    "match_id": 97,
    "match_number": 97,
    "stage": "Quarts de finale",
    "home_placeholder": "W89",
    "away_placeholder": "W90",
    "home_team": "",
    "home_code": "",
    "home_flag": "",
    "away_team": "",
    "away_code": "",
    "away_flag": "",
    "home_score_real": "",
    "away_score_real": "",
    "result_real": "",
    "shootout_winner": "",
    "pred_home_win": "",
    "pred_draw": "",
    "pred_away_win": "",
    "date": "Jeudi 9 juillet (22 heures)",
    "city": "Boston",
    "next_match_id": 101,
    "is_home_in_next": true,
    "loser_next_match_id": null,
    "is_loser_home_in_next": null
  },
  {
    "match_id": 98,
    "match_number": 98,
    "stage": "Quarts de finale",
    "home_placeholder": "W93",
    "away_placeholder": "W94",
    "home_team": "",
    "home_code": "",
    "home_flag": "",
    "away_team": "",
    "away_code": "",
    "away_flag": "",
    "home_score_real": "",
    "away_score_real": "",
    "result_real": "",
    "shootout_winner": "",
    "pred_home_win": "",
    "pred_draw": "",
    "pred_away_win": "",
    "date": "Vendredi 10 juillet (21 heures)",
    "city": "Los Angeles",
    "next_match_id": 101,
    "is_home_in_next": false,
    "loser_next_match_id": null,
    "is_loser_home_in_next": null
  },
  {
    "match_id": 99,
    "match_number": 99,
    "stage": "Quarts de finale",
    "home_placeholder": "W91",
    "away_placeholder": "W92",
    "home_team": "",
    "home_code": "",
    "home_flag": "",
    "away_team": "",
    "away_code": "",
    "away_flag": "",
    "home_score_real": "",
    "away_score_real": "",
    "result_real": "",
    "shootout_winner": "",
    "pred_home_win": "",
    "pred_draw": "",
    "pred_away_win": "",
    "date": "Samedi 11 juillet (23 heures)",
    "city": "Miami",
    "next_match_id": 102,
    "is_home_in_next": true,
    "loser_next_match_id": null,
    "is_loser_home_in_next": null
  },
  {
    "match_id": 100,
    "match_number": 100,
    "stage": "Quarts de finale",
    "home_placeholder": "W95",
    "away_placeholder": "W100",
    "home_team": "",
    "home_code": "",
    "home_flag": "",
    "away_team": "",
    "away_code": "",
    "away_flag": "",
    "home_score_real": "",
    "away_score_real": "",
    "result_real": "",
    "shootout_winner": "",
    "pred_home_win": "",
    "pred_draw": "",
    "pred_away_win": "",
    "date": "Dimanche 12 juillet (3 heures du matin)",
    "city": "Kansas City",
    "next_match_id": 102,
    "is_home_in_next": false,
    "loser_next_match_id": null,
    "is_loser_home_in_next": null
  },
  {
    "match_id": 101,
    "match_number": 101,
    "stage": "Demi-finales",
    "home_placeholder": "W97",
    "away_placeholder": "W98",
    "home_team": "",
    "home_code": "",
    "home_flag": "",
    "away_team": "",
    "away_code": "",
    "away_flag": "",
    "home_score_real": "",
    "away_score_real": "",
    "result_real": "",
    "shootout_winner": "",
    "pred_home_win": "",
    "pred_draw": "",
    "pred_away_win": "",
    "date": "Mardi 14 juillet (21 heures)",
    "city": "Dallas",
    "next_match_id": 104,
    "is_home_in_next": true,
    "loser_next_match_id": 103,
    "is_loser_home_in_next": true
  },
  {
    "match_id": 102,
    "match_number": 102,
    "stage": "Demi-finales",
    "home_placeholder": "W99",
    "away_placeholder": "W100",
    "home_team": "",
    "home_code": "",
    "home_flag": "",
    "away_team": "",
    "away_code": "",
    "away_flag": "",
    "home_score_real": "",
    "away_score_real": "",
    "result_real": "",
    "shootout_winner": "",
    "pred_home_win": "",
    "pred_draw": "",
    "pred_away_win": "",
    "date": "Mercredi 15 juillet (21 heures)",
    "city": "Atlanta",
    "next_match_id": 104,
    "is_home_in_next": false,
    "loser_next_match_id": 103,
    "is_loser_home_in_next": false
  },
  {
    "match_id": 103,
    "match_number": 103,
    "stage": "Match pour la 3e place",
    "home_placeholder": "RU101",
    "away_placeholder": "RU102",
    "home_team": "",
    "home_code": "",
    "home_flag": "",
    "away_team": "",
    "away_code": "",
    "away_flag": "",
    "home_score_real": "",
    "away_score_real": "",
    "result_real": "",
    "shootout_winner": "",
    "pred_home_win": "",
    "pred_draw": "",
    "pred_away_win": "",
    "date": "Samedi 18 juillet (23 heures)",
    "city": "Miami",
    "next_match_id": null,
    "is_home_in_next": null,
    "loser_next_match_id": null,
    "is_loser_home_in_next": null
  },
  {
    "match_id": 104,
    "match_number": 104,
    "stage": "Finale",
    "home_placeholder": "W101",
    "away_placeholder": "W102",
    "home_team": "",
    "home_code": "",
    "home_flag": "",
    "away_team": "",
    "away_code": "",
    "away_flag": "",
    "home_score_real": "",
    "away_score_real": "",
    "result_real": "",
    "shootout_winner": "",
    "pred_home_win": "",
    "pred_draw": "",
    "pred_away_win": "",
    "date": "Dimanche 19 juillet (21 heures)",
    "city": "New York/New Jersey",
    "next_match_id": null,
    "is_home_in_next": null,
    "loser_next_match_id": null,
    "is_loser_home_in_next": null
  }
]